radiomesh/__init__.py
radiomesh/constants.py
radiomesh/core.py
radiomesh/es_kernel.py
radiomesh/gridding.py
radiomesh/product.py
radiomesh/tests/__init__.py
radiomesh/tests/cmp_vs_ducc.py
radiomesh/tests/test_core.py
radiomesh/tests/test_float_literal.py
radiomesh/tests/test_wgrid.py
radiomesh-0.1.1.dist-info/METADATA
radiomesh-0.1.1.dist-info/WHEEL
radiomesh-0.1.1.dist-info/licenses/LICENSE
radiomesh-0.1.1.dist-info/RECORD
