Metadata-Version: 2.4
Name: radiomesh
Version: 0.1.1
Summary: Just a basic numba gridder
Author-email: Landman Bester <lbester@sarao.ac.za>, Simon Perkins <sperkins@sarao.ac.za>
License: MIT
License-File: LICENSE
Requires-Python: <3.14,>=3.10
Requires-Dist: numba>=0.60.0
Requires-Dist: numpy>=2.0.0
Requires-Dist: scipy
Requires-Dist: sympy>=1.9
Provides-Extra: dev
Requires-Dist: pre-commit>=4.2.0; extra == 'dev'
Requires-Dist: tbump>=6.11.0; extra == 'dev'
Provides-Extra: testing
Requires-Dist: pytest>=8.4.1; extra == 'testing'
